aiida_ddec/__init__.py
aiida_ddec/calculations/__init__.py
aiida_ddec/parsers/__init__.py
aiida_ddec/utils/__init__.py
aiida_ddec/utils/workchains.py
aiida_ddec/utils/xyzparser.py
aiida_ddec/workchains/__init__.py
aiida_ddec/workchains/cp2k_ddec.py
aiida_ddec-2.0.0.dist-info/entry_points.txt
aiida_ddec-2.0.0.dist-info/LICENSE
aiida_ddec-2.0.0.dist-info/WHEEL
aiida_ddec-2.0.0.dist-info/METADATA
aiida_ddec-2.0.0.dist-info/RECORD
