Metadata-Version: 2.1
Name: aiida-ddec
Version: 2.0.0
Summary: AiiDA plugin for DDEC code
Keywords: aiida,workflows
Author-email: Aliaksandr Yakutovich <aliaksandr.yakutovich@epfl.ch>, Miriam Pougin <miriam.pougin@epfl.ch>
Requires-Python: >=3.8
Classifier: Development Status :: 5 - Production/Stable
Classifier: Framework :: AiiDA
Classifier: License :: OSI Approved :: MIT License
Classifier: Programming Language :: Python
Classifier: Programming Language :: Python :: 3.8
Classifier: Programming Language :: Python :: 3.9
Classifier: Programming Language :: Python :: 3.10
Classifier: Programming Language :: Python :: 3.11
Requires-Dist: aiida-core[atomic_tools]~=2.3
Requires-Dist: aiida-cp2k~=2.0
Requires-Dist: six
Requires-Dist: voluptuous
Requires-Dist: importlib_resources
Requires-Dist: pre-commit~=3.3 ; extra == "pre-commit"
Requires-Dist: black~=23.7 ; extra == "pre-commit"
Requires-Dist: isort~=5.12 ; extra == "pre-commit"
Requires-Dist: pylint~=2.17 ; extra == "pre-commit"
Requires-Dist: pgtest~=1.3.1 ; extra == "tests"
Requires-Dist: aiida-testing-dev==0.1.0.dev1 ; extra == "tests"
Requires-Dist: pytest-cov~=2.7 ; extra == "tests"
Requires-Dist: pytest~=6.0 ; extra == "tests"
Project-URL: Homepage, https://github.com/lsmo-epfl/aiida-ddec
Provides-Extra: pre-commit
Provides-Extra: tests
